maleo/types/__init__.py
maleo/types/any.py
maleo/types/boolean.py
maleo/types/bytes.py
maleo/types/datetime.py
maleo/types/dict.py
maleo/types/enum.py
maleo/types/float.py
maleo/types/integer.py
maleo/types/mapping.py
maleo/types/misc.py
maleo/types/primitive.py
maleo/types/string.py
maleo/types/uuid.py
maleo_types-0.0.26.dist-info/licenses/LICENSE
maleo_types-0.0.26.dist-info/METADATA
maleo_types-0.0.26.dist-info/WHEEL
maleo_types-0.0.26.dist-info/top_level.txt
maleo_types-0.0.26.dist-info/RECORD
